oaxaca/__init__.py
oaxaca/formulaic_utils.py
oaxaca/oaxaca.py
oaxaca/results.py
oaxaca-1.0.3.dist-info/METADATA
oaxaca-1.0.3.dist-info/WHEEL
oaxaca-1.0.3.dist-info/licenses/LICENSE
oaxaca-1.0.3.dist-info/RECORD
