Metadata-Version: 2.4
Name: oaxaca
Version: 1.0.3
Summary: Oaxaca Blinder decomposition
Project-URL: Homepage, https://anhqle.github.io/oaxaca/
Project-URL: Repository, https://github.com/anhqle/oaxaca
Project-URL: Documentation, https://anhqle.github.io/oaxaca/
Author-email: Anh Le <anh.le91@gmail.com>
License-File: LICENSE
Keywords: python
Classifier: Intended Audience :: Developers
Classifier: Programming Language :: Python
Classifier: Programming Language :: Python :: 3
Classifier: Programming Language :: Python :: 3.9
Classifier: Programming Language :: Python :: 3.10
Classifier: Programming Language :: Python :: 3.11
Classifier: Programming Language :: Python :: 3.12
Classifier: Programming Language :: Python :: 3.13
Classifier: Topic :: Software Development :: Libraries :: Python Modules
Requires-Python: <4.0,>=3.9
Requires-Dist: formulaic>=1.2.0
Requires-Dist: pandas>=1.0.0
Requires-Dist: statsmodels>=0.14.5
